{
    "bounds": "[300,1416][717,1548]", 
    "checkable": false, 
    "checked": false, 
    "class": "android.widget.Button", 
    "clickable": true, 
    "content-desc": "not favorited", 
    "enabled": true, 
    "focusable": true, 
    "focused": false, 
    "hash": "6Hun3BozduRVSNLf5cgEBw==\n", 
    "height": 132, 
    "hier_level": 15, 
    "human_hash": "android.widget.Button_X300_Y1416_W417_H132", 
    "human_readable": "android.widget.Button_300_1416_417_132_android.widget.Button_ffffffffffffc0019ffd1f3f00210001000100019ffffa898001ffffffffffff_18b88334b4ff86e24ffc454e0091e94c", 
    "image_path": "ZDU0MTRmYzM3YTljNDkwNmVlYmE5NDZlZjhmY2JiNmI.png", 
    "index": "1", 
    "is_transformed": true, 
    "long-clickable": false, 
    "password": false, 
    "resource-id": "com.chewy.android:id/actionButton", 
    "screen_hash": "6dcdd47321d3a1976810dfe843f70ae0", 
    "scrollable": false, 
    "selected": false, 
    "tag_name": "android.widget.Button", 
    "text": "Add to Favorites", 
    "width": 417, 
    "x": 300, 
    "y": 1416
}