{
    "bounds": "[55,1950][245,2082]", 
    "checkable": false, 
    "checked": false, 
    "class": "android.widget.Button", 
    "clickable": true, 
    "enabled": true, 
    "focusable": true, 
    "focused": false, 
    "hash": "k6VP6LiSXJ4/mUD6Di1vPQ==\n", 
    "height": 132, 
    "hier_level": 13, 
    "human_hash": "android.widget.Button_X55_Y1950_W190_H132", 
    "human_readable": "android.widget.Button_55_1950_190_132_android.widget.Button_ffffffffffffffffffffffffc7efc023c021c023f8ffffffffffffffffffffff_0ffc71968c588734b47b6925f63858c5", 
    "image_path": "ZWQ0ZGRlZDE0N2MyZTFlZmMzNzY2ZDJlM2QzY2ZmNzg.png", 
    "index": "0", 
    "is_transformed": true, 
    "long-clickable": false, 
    "password": false, 
    "resource-id": "com.chewy.android:id/signInButton", 
    "screen_hash": "e8fbbaa2acabba4882cbc862dda87027", 
    "scrollable": false, 
    "selected": false, 
    "tag_name": "android.widget.Button", 
    "text": "Sign In", 
    "width": 190, 
    "x": 55, 
    "y": 1950
}